{
  "MapName": "woods",
  "Zones": {
    "Zone_UniWoodBorder": [
      {
        "x": -512.4608,
        "y": 15.06141,
        "z": -540.1332
      },
      {
        "x": -498.9173,
        "y": 15.76141,
        "z": -530.1361
      },
      {
        "x": 93.17213,
        "y": 16.67556,
        "z": -844.7047
      },
      {
        "x": 233.3309,
        "y": 11.33148,
        "z": -835.4743
      },
      {
        "x": 426.0655,
        "y": 12.17392,
        "z": -597.9388
      },
      {
        "x": 438.2757,
        "y": 1.05803,
        "z": -172.2979
      },
      {
        "x": 474.613,
        "y": -4.767283,
        "z": -55.06424
      },
      {
        "x": 348.9348,
        "y": -12.5098,
        "z": 334.0098
      },
      {
        "x": -520.704,
        "y": -1.243579,
        "z": 290.6529
      },
      {
        "x": -532.5609,
        "y": 7.15378,
        "z": 156.7161
      },
      {
        "x": -551.3846,
        "y": 9.416579,
        "z": -84.53111
      },
      {
        "x": -624.7372,
        "y": 13.02934,
        "z": -261.2275
      },
      {
        "x": 16.54523,
        "y": -16.31178,
        "z": 90.07208
      },
      {
        "x": 9.558798,
        "y": -16.05365,
        "z": 91.96134
      },
      {
        "x": 185.2371,
        "y": -15.80674,
        "z": 213.6441
      },
      {
        "x": -92.70631,
        "y": -16.80265,
        "z": 244.639
      }
    ],
    "Zone_UniWoodOne": [
      {
        "x": 411.6742,
        "y": -13.63958,
        "z": 234.2545
      },
      {
        "x": 446.2213,
        "y": -14.2454,
        "z": 68.74946
      },
      {
        "x": 371.3483,
        "y": -10.44824,
        "z": 122.2118
      },
      {
        "x": 229.3623,
        "y": -2.215179,
        "z": -74.37692
      },
      {
        "x": 239.6324,
        "y": -8.283291,
        "z": 121.8405
      },
      {
        "x": -177.5623,
        "y": -0.7057828,
        "z": 383.6689
      },
      {
        "x": -405.7312,
        "y": -1.181719,
        "z": 312.299
      },
      {
        "x": -446.533,
        "y": 6.361684,
        "z": 61.44395
      },
      {
        "x": -180.4451,
        "y": -1.864982,
        "z": 255.1175
      },
      {
        "x": -196.8581,
        "y": -1.872594,
        "z": 217.2836
      },
      {
        "x": -390.1763,
        "y": 7.439628,
        "z": 20.08298
      },
      {
        "x": -326.8017,
        "y": 14.54534,
        "z": 21.281
      },
      {
        "x": -261.3188,
        "y": 9.73388,
        "z": -37.95701
      },
      {
        "x": -22.01088,
        "y": -3.677858,
        "z": 50.20686
      },
      {
        "x": 62.03809,
        "y": -7.677126,
        "z": 61.92856
      },
      {
        "x": 48.81469,
        "y": -3.677855, 
        "z": -4.675363
      },
      {
        "x": 78.50536,
        "y": -1.779578,
        "z": -45.35608
      },
      {
        "x": -1.927716,
        "y": -1.678226,
        "z": -77.75195
      },
      {
        "x": 28.8674,
        "y": 5.054286,
        "z": -114.5336
      },
      {
        "x": 284.1323,
        "y": 22.90646,
        "z": -443.0842
      }
    ],
    "Zone_UniWoodTwo": [
      {
        "x": 314.3675,
        "y": 22.86041,
        "z": -464.3273
      },
      {
        "x": 279.9002,
        "y": 22.88321,
        "z": -514.4941
      },
      {
        "x": 225.2759,
        "y": 24.28225, 
        "z": -706.1436
      },
      {
        "x": 127.8479,
        "y": 24.39942,
        "z": -742.3547
      },
      {
        "x": -13.48547,
        "y": 11.56957,
        "z": -749.7518
      },
      {
        "x": -74.48624,
        "y": 12.02806,
        "z": -717.3958
      },
      {
        "x": -119.4829,
        "y": 10.47889,
        "z": -690.9995
      },
      {
        "x": -117.6232,
        "y": 9.024709,
        "z": -639.8456
      },
      {
        "x": -91.51072,
        "y": 8.040844,
        "z": -609.0873
      },
      {
        "x": -453.1656,
        "y": 15.02456,
        "z": -405.8477
      },
      {
        "x": -506.1613,
        "y": 14.96298,
        "z": -379.9472
      },
      {
        "x": -458.4531,
        "y": 15.04399,
        "z": -356.0404
      },
      {
        "x": -473.353,
        "y": 21.54251,
        "z": -230.1927
      },
      {
        "x": -547.3179,
        "y": 15.03852,
        "z": -204.3824
      },
      {
        "x": -509.8777,
        "y": 15.91537,
        "z": -175.9144
      },
      {
        "x": -480.566,
        "y": 14.83668,
        "z": -154.4397
      },
      {
        "x": -311.6758,
        "y": -0.3280295,
        "z": 238.9678
      },
      {
        "x": -234.2555,
        "y": -1.488227,
        "z": 348.9875
      },
      {
        "x": -62.83794,
        "y": -2.570747,
        "z": 366.5986
      },
      {
        "x": -89.007,
        "y": -4.677653,
        "z": 144.1618
      },
      {
        "x": -44.44151,
        "y": 4.848052,
        "z": -24.55703 
      },
      {
        "x": 147.6118,
        "y": -2.609811,
        "z": 17.95774
      },
      {
        "x": -44.44151,
        "y": 4.848052,
        "z": -24.55703
      },
      {
        "x": 147.6118,
        "y": -2.609811,
        "z": 17.95774
      }
    ],
    "Zone_UniWoodThree": [
      {
        "x": -382.6678,
        "y": 1.843037,
        "z": 198.5256
      },
      {
        "x": -178.0742,
        "y": 0.8812871,
        "z": 417.9139
      },
      {
        "x": 121.1456,
        "y": -2.044228,
        "z": 61.70916
      },
      {
        "x": 119.9483,
        "y": -3.677855,
        "z": -7.407207
      },
      {
        "x": -28.8509,
        "y": 9.318425,
        "z": -136.6598
      },
      {
        "x": -36.97943,
        "y": 4.883998,
        "z": -52.53815
      },
      {
        "x": -47.86731,
        "y": 4.087847,
        "z": 21.93862
      },
      {
        "x": -253.6547,
        "y": 6.873779,
        "z": 75.41897
      },
      {
        "x": 255.5928,
        "y": -8.357802,
        "z": 125.3803
      },
      {
        "x": 70.93587,
        "y": -4.677674,
        "z": -65.6062
      },
      {
        "x": 230.9817,
        "y": 0.3319879,
        "z": -139.5328
      },
      {
        "x": 51.79022,
        "y": 5.366237,
        "z": -136.5196
      },
      {
        "x": 5.193851,
        "y": -2.344957,
        "z": -57.46371
      },
      {
        "x": -1.81324,
        "y": -3.363332,
        "z": 29.50492
      },
      {
        "x": -35.91174,
        "y": 8.382738,
        "z": -593.6514
      },
      {
        "x": -128.6551,
        "y": -8.518773,
        "z": 248.2787
      },
      {
        "x": -156.507,
        "y": -3.892275,
        "z": 231.5748
      },
      {
        "x": 440.1851,
        "y": -18.48022,
        "z": 221.8747
      },
      {
        "x": 427.0241,
        "y": -10.05958,
        "z": 79.21545
      }
    ]
  }
}